{"Modules":[{"Key":"oktapolicyrule","Source":"./modules/okta-auth-server-policy-rule","Dir":"modules/okta-auth-server-policy-rule"},{"Key":"","Source":"","Dir":"."},{"Key":"oktaserviceapp","Source":"./modules/okta-service-app","Dir":"modules/okta-service-app"},{"Key":"oktawebapp","Source":"./modules/okta-web-app","Dir":"modules/okta-web-app"},{"Key":"oktagroup1","Source":"./modules/okta-group","Dir":"modules/okta-group"},{"Key":"oktagroup","Source":"./modules/okta-group","Dir":"modules/okta-group"},{"Key":"oktaspaapp","Source":"./modules/okta-spa-app","Dir":"modules/okta-spa-app"},{"Key":"oktascope","Source":"./modules/okta-auth-server-scope","Dir":"modules/okta-auth-server-scope"},{"Key":"oktapolicy","Source":"./modules/okta-auth-server-policy","Dir":"modules/okta-auth-server-policy"},{"Key":"oktasamlapp","Source":"./modules/okta-saml-app","Dir":"modules/okta-saml-app"},{"Key":"oktaauthserver","Source":"./modules/okta-auth-sever","Dir":"modules/okta-auth-sever"}]}